offre/__init__.py
offre/__main__.py
offre/candidate.py
offre/provider.py
offre/py.typed
offre/reporter.py
offre/requirement.py
offre-0.0.2.dist-info/LICENSE
offre-0.0.2.dist-info/WHEEL
offre-0.0.2.dist-info/METADATA
offre-0.0.2.dist-info/RECORD
