Metadata-Version: 2.1
Name: offre
Version: 0.0.2
Summary: Python, m'offre qqch!
Home-page: https://sr.ht/~cnx/offre
License: AGPLv3+
Keywords: python,download,distribution
Author: Nguyễn Gia Phong
Author-email: mcsinyx@disroot.org
Requires-Python: >=3.7
Classifier: Development Status :: 1 - Planning
Classifier: Environment :: Console
Classifier: Intended Audience :: Developers
Classifier: Intended Audience :: End Users/Desktop
Classifier: License :: OSI Approved :: GNU Affero General Public License v3 or later (AGPLv3+)
Classifier: Natural Language :: English
Classifier: Operating System :: OS Independent
Classifier: Programming Language :: Python :: 3 :: Only
Classifier: Programming Language :: Python :: 3.7
Classifier: Programming Language :: Python :: 3.8
Classifier: Programming Language :: Python :: 3.9
Classifier: Topic :: Utilities
Classifier: Typing :: Typed
Requires-Dist: distlib
Requires-Dist: html5lib
Requires-Dist: httpx[http2]
Requires-Dist: packaging
Requires-Dist: resolvelib>=0.5.1
Requires-Dist: trio
